<?xml version = '1.0' encoding = 'UTF-8'?>
<TableSpaceOraclev10g class="oracle.dbtools.crest.model.design.storage.oracle.v10g.TableSpaceOraclev10g" name="TBS01" id="1AD7192A-BA21-0B4D-9E5C-5063D2C6B2F3" directorySegmentName="seg_0">
<sourceConnName>RMGR@EXADWHPROD</sourceConnName>
<sourceObjSchema>RMGR</sourceObjSchema>
<sourceObjName>TBS01</sourceObjName>
<createdBy>nkarag</createdBy>
<createdTime>2012-08-16 13:42:13 UTC</createdTime>
<ownerDesignName>rmgr_data_model</ownerDesignName>
<emUniformSize>0</emUniformSize>
<extentManagement>LOCAL</extentManagement>
</TableSpaceOraclev10g>